toypandas/__init__.py
toypandas/dataframe.py
toypandas/series.py
toypandas-0.2.0.dist-info/METADATA
toypandas-0.2.0.dist-info/WHEEL
toypandas-0.2.0.dist-info/licenses/LICENSE
toypandas-0.2.0.dist-info/RECORD
